llm_few_shot_gen/__about__.py
llm_few_shot_gen/__init__.py
llm_few_shot_gen/constants.py
llm_few_shot_gen/generators.py
llm_few_shot_gen/models/__init__.py
llm_few_shot_gen/models/output.py
llm_few_shot_gen/models/prompt_engineering.py
llm_few_shot_gen-0.1.2.dist-info/METADATA
llm_few_shot_gen-0.1.2.dist-info/WHEEL
llm_few_shot_gen-0.1.2.dist-info/licenses/LICENSE.txt
llm_few_shot_gen-0.1.2.dist-info/RECORD
